pyroxide.py
pyroxide-0.2.dist-info/LICENSE.txt
pyroxide-0.2.dist-info/METADATA
pyroxide-0.2.dist-info/WHEEL
pyroxide-0.2.dist-info/top_level.txt
pyroxide-0.2.dist-info/RECORD
